openg2p_g2p_bridge_example_bank_api/__init__.py
openg2p_g2p_bridge_example_bank_api/app.py
openg2p_g2p_bridge_example_bank_api/celery_app.py
openg2p_g2p_bridge_example_bank_api/config.py
openg2p_g2p_bridge_example_bank_api/controllers/__init__.py
openg2p_g2p_bridge_example_bank_api/controllers/account_statement.py
openg2p_g2p_bridge_example_bank_api/controllers/block_funds.py
openg2p_g2p_bridge_example_bank_api/controllers/check_available_funds.py
openg2p_g2p_bridge_example_bank_api/controllers/initiate_payment.py
openg2p_g2p_bridge_example_bank_api/controllers/ussd_controller.py
openg2p_g2p_bridge_example_bank_api/utils/__init__.py
openg2p_g2p_bridge_example_bank_api-1.1.0.dist-info/METADATA
openg2p_g2p_bridge_example_bank_api-1.1.0.dist-info/WHEEL
openg2p_g2p_bridge_example_bank_api-1.1.0.dist-info/licenses/LICENSE
openg2p_g2p_bridge_example_bank_api-1.1.0.dist-info/RECORD
